scClassifier2/__init__.py
scClassifier2/scClassifier2.py
scClassifier2/utils/__init__.py
scClassifier2/utils/custom_mlp.py
scClassifier2/utils/mnist_cached.py
scClassifier2/utils/scdata_cached.py
scClassifier2/utils/vae_plots.py
scClassifier2-0.0.13.dist-info/LICENSE.txt
scClassifier2-0.0.13.dist-info/METADATA
scClassifier2-0.0.13.dist-info/WHEEL
scClassifier2-0.0.13.dist-info/entry_points.txt
scClassifier2-0.0.13.dist-info/top_level.txt
scClassifier2-0.0.13.dist-info/RECORD
