Metadata-Version: 2.1
Name: scClassifier2
Version: 0.0.13
Summary: a tool for single cell data
Home-page: UNKNOWN
Author: zengBio
License: MIT
Platform: UNKNOWN
Classifier: Programming Language :: Python :: 3
Classifier: License :: OSI Approved :: MIT License
Classifier: Operating System :: OS Independent
Requires-Python: >=3.6
License-File: LICENSE.txt
Requires-Dist: numpy
Requires-Dist: pandas
Requires-Dist: pyro-ppl
Requires-Dist: scikit-learn
Requires-Dist: scipy
Requires-Dist: matplotlib
Requires-Dist: seaborn
